{
	"credit": "Made with Blockbench",
	"parent": "minecraft:block/cube_bottom_top",
	"render_type": "cutout",
	"textures": {
		"side_nsew": "warp_pipes:block/clear_warp_pipe/clear_warp_pipe_side_nsew",
		"inner_nsew": "warp_pipes:block/clear_warp_pipe/clear_warp_pipe_side_inner_nsew",
		"particle": "warp_pipes:block/clear_warp_pipe/clear_warp_pipe_side"
	},
	"elements": [
		{
			"name": "north",
			"from": [0, 0, 0],
			"to": [16, 16, 3],
			"rotation": {"angle": 0, "axis": "y", "origin": [8, 8, 8]},
			"faces": {
				"north": {"uv": [16, 0, 0, 16], "texture": "#side_nsew", "cullface": "north"},
				"south": {"uv": [0, 0, 16, 16], "texture": "#inner_nsew"}
			}
		},
		{
			"name": "south",
			"from": [0, 0, 13],
			"to": [16, 16, 16],
			"rotation": {"angle": 0, "axis": "y", "origin": [8, 8, 8]},
			"faces": {
				"north": {"uv": [16, 0, 0, 16], "texture": "#inner_nsew"},
				"south": {"uv": [0, 0, 16, 16], "texture": "#side_nsew", "cullface": "south"}
			}
		}
	]
}